{
  "type": "Feature",
  "properties": {
    "iso:country":"AR",
    "sg:address":"Vera 15 3-B",
    "sg:city":"Ciudad de Buenos Aires",
    "sg:classifiers":[
        {
            "category":"Professional",
            "subcategory":"Computer Services",
            "type":"Services"
        }
    ],
    "sg:postcode":"1414",
    "sg:tags":[
        "video",
        "image",
        "reviews",
        "online",
        "collaboration",
        "design-review",
        "design-feedback",
        "visual-feedback"
    ],
    "sg:website":"http://www.creationflow.com",
    "wof:name":"CreationFlow",
    "wof:placetype":"venue"
},
  "geometry": {"coordinates":[-58.4339539,-34.6028583],"type":"Point"}
}